CHANGES.txt
MANIFEST.in
README.txt
setup.py
collective/__init__.py
collective.js.trunk8.egg-info/PKG-INFO
collective.js.trunk8.egg-info/SOURCES.txt
collective.js.trunk8.egg-info/dependency_links.txt
collective.js.trunk8.egg-info/entry_points.txt
collective.js.trunk8.egg-info/namespace_packages.txt
collective.js.trunk8.egg-info/not-zip-safe
collective.js.trunk8.egg-info/requires.txt
collective.js.trunk8.egg-info/top_level.txt
collective/js/__init__.py
collective/js/trunk8/__init__.py
collective/js/trunk8/configure.zcml
collective/js/trunk8/profiles/default/jsregistry.xml
collective/js/trunk8/profiles/default/metadata.xml
collective/js/trunk8/resources/trunk8.js